{
    "clientHtmlFile":  "C:\\vscode\\tech-legal\\tech-legal\\scripts\\affg-sow004-rev2-client-preview.html",
    "envelopeId":  "e3cc8d1a-1487-89ba-83dc-1c0fbefad2b9",
    "preparedAt":  "2026-04-20T12:15:01.4109449-07:00",
    "signerEmail":  "rjain@technijian.com",
    "clientName":  "Iris Liu",
    "emailSubject":  "Technijian - SOW-AFFG-004 Rev 1 - Signature Required",
    "clientEmail":  "iris.liu@americanfundstars.com",
    "techHtmlFile":  "C:\\vscode\\tech-legal\\tech-legal\\scripts\\affg-sow004-rev2-tech-preview.html",
    "signerName":  "Ravi Jain"
}
